LICENSE
MANIFEST.in
README.md
setup.py
dumpserver/__init__.py
dumpserver/addonmanager.py
dumpserver/certs.py
dumpserver/command.py
dumpserver/command_lexer.py
dumpserver/connection.py
dumpserver/ctx.py
dumpserver/eventsequence.py
dumpserver/exceptions.py
dumpserver/flow.py
dumpserver/flowfilter.py
dumpserver/hooks.py
dumpserver/http.py
dumpserver/log.py
dumpserver/master.py
dumpserver/options.py
dumpserver/optmanager.py
dumpserver/py.typed
dumpserver/stateobject.py
dumpserver/tcp.py
dumpserver/tls.py
dumpserver/types.py
dumpserver/version.py
dumpserver/websocket.py
dumpserver.egg-info/PKG-INFO
dumpserver.egg-info/SOURCES.txt
dumpserver.egg-info/dependency_links.txt
dumpserver.egg-info/requires.txt
dumpserver.egg-info/top_level.txt
dumpserver/addons/__init__.py
dumpserver/addons/anticache.py
dumpserver/addons/anticomp.py
dumpserver/addons/asgiapp.py
dumpserver/addons/block.py
dumpserver/addons/blocklist.py
dumpserver/addons/browser.py
dumpserver/addons/clientplayback.py
dumpserver/addons/command_history.py
dumpserver/addons/comment.py
dumpserver/addons/core.py
dumpserver/addons/cut.py
dumpserver/addons/disable_h2c.py
dumpserver/addons/dumper.py
dumpserver/addons/errorcheck.py
dumpserver/addons/eventstore.py
dumpserver/addons/export.py
dumpserver/addons/intercept.py
dumpserver/addons/keepserving.py
dumpserver/addons/maplocal.py
dumpserver/addons/mapremote.py
dumpserver/addons/modifybody.py
dumpserver/addons/modifyheaders.py
dumpserver/addons/next_layer.py
dumpserver/addons/onboarding.py
dumpserver/addons/proxyauth.py
dumpserver/addons/proxyserver.py
dumpserver/addons/readfile.py
dumpserver/addons/save.py
dumpserver/addons/script.py
dumpserver/addons/serverplayback.py
dumpserver/addons/stickyauth.py
dumpserver/addons/stickycookie.py
dumpserver/addons/termlog.py
dumpserver/addons/tlsconfig.py
dumpserver/addons/upstream_auth.py
dumpserver/addons/view.py
dumpserver/addons/onboardingapp/__init__.py
dumpserver/contentviews/__init__.py
dumpserver/contentviews/auto.py
dumpserver/contentviews/base.py
dumpserver/contentviews/css.py
dumpserver/contentviews/graphql.py
dumpserver/contentviews/grpc.py
dumpserver/contentviews/hex.py
